MANIFEST.in
README
setup.py
timetra/__init__.py
timetra/notification.py
timetra/storage.py
timetra/term.py
timetra/timer.py
timetra/utils.py
timetra.egg-info/PKG-INFO
timetra.egg-info/SOURCES.txt
timetra.egg-info/dependency_links.txt
timetra.egg-info/not-zip-safe
timetra.egg-info/requires.txt
timetra.egg-info/top_level.txt
timetra/cli/__init__.py
timetra/curses/__init__.py
timetra/curses/widgets.py
timetra/reporting/__init__.py
timetra/reporting/drift.py
timetra/reporting/methodology.py
timetra/reporting/prediction.py
timetra/web/__init__.py
timetra/web/static/css/bootstrap.min.css
timetra/web/static/img/glyphicons-halflings-white.png
timetra/web/static/img/glyphicons-halflings.png
timetra/web/templates/_formhelpers.html
timetra/web/templates/_helpers.html
timetra/web/templates/activity.html
timetra/web/templates/add.html
timetra/web/templates/base.html
timetra/web/templates/dashboard.html
timetra/web/templates/day.html
timetra/web/templates/drift.html
timetra/web/templates/edit.html
timetra/web/templates/predictions.html
timetra/web/templates/search.html